{"data":{"indexs":["RedmiNote4X(mido)"],"resources":[{"name":"所有重启","RedmiNote4X(mido)":"0.0089","RedmiNote4X(mido)-attach":{"show":{"报活人数":2583,"出现次数":23},"conf":{"nextUrl":"/mqsas/excp/dashboard/category.do?bigCategory=restart","hasDetail":"true"}}},{"name":"应用崩溃","RedmiNote4X(mido)":"0.2772","RedmiNote4X(mido)-attach":{"show":{"报活人数":2583,"出现次数":716},"conf":{"nextUrl":"/mqsas/excp/dashboard/category.do?bigCategory=app_crash","hasDetail":"true"}}},{"name":"应用无响应","RedmiNote4X(mido)":"0.0534","RedmiNote4X(mido)-attach":{"show":{"报活人数":2583,"出现次数":138},"conf":{"nextUrl":"/mqsas/excp/dashboard/category.do?bigCategory=no_response","hasDetail":"true"}}},{"name":"冻屏","RedmiNote4X(mido)":"0.0054","RedmiNote4X(mido)-attach":{"show":{"报活人数":2583,"出现次数":14},"conf":{"nextUrl":"/mqsas/excp/dashboard/category.do?bigCategory=screen_frozen","hasDetail":"true"}}}]},"status":"true"}