{"data":[{"alarmLevel":"UNKNOW_TYPE","alarmStatus":"","benchmarkPerformIndex":"","benchmarkVersion":"","changeDetail":"","children":[],"component":"","currentVersion":"7.9.14","date":"","expType":"UNKNOW_TYPE","id":5730691,"indexType":"","model":"MI5(gemini)","monitorType":"","performExtIndex":"","performIndex":"1224.88","performIndexInc":"","pkn":"com.xiaomi.smarthome"},{"alarmLevel":"UNKNOW_TYPE","alarmStatus":"","benchmarkPerformIndex":"","benchmarkVersion":"","changeDetail":"","children":[],"component":"","currentVersion":"7.9.14","date":"","expType":"UNKNOW_TYPE","id":5729611,"indexType":"","model":"MI5X(tiffany)","monitorType":"","performExtIndex":"","performIndex":"895.00","performIndexInc":"","pkn":"com.xiaomi.smarthome"},{"alarmLevel":"UNKNOW_TYPE","alarmStatus":"","benchmarkPerformIndex":"","benchmarkVersion":"","changeDetail":"","children":[],"component":"","currentVersion":"7.9.14","date":"","expType":"UNKNOW_TYPE","id":5730081,"indexType":"","model":"MI6(sagit)","monitorType":"","performExtIndex":"","performIndex":"557.67","performIndexInc":"","pkn":"com.xiaomi.smarthome"},{"alarmLevel":"UNKNOW_TYPE","alarmStatus":"","benchmarkPerformIndex":"","benchmarkVersion":"","changeDetail":"","children":[],"component":"","currentVersion":"7.9.14","date":"","expType":"UNKNOW_TYPE","id":5730370,"indexType":"","model":"RedmiNote4X(mido)","monitorType":"","performExtIndex":"","performIndex":"1404.23","performIndexInc":"","pkn":"com.xiaomi.smarthome"},{"alarmLevel":"UNKNOW_TYPE","alarmStatus":"","benchmarkPerformIndex":"","benchmarkVersion":"","changeDetail":"","children":[],"component":"","currentVersion":"7.9.14","date":"","expType":"UNKNOW_TYPE","id":5729290,"indexType":"","model":"RedmiNote5A(ugg)","monitorType":"","performExtIndex":"","performIndex":"854.90","performIndexInc":"","pkn":"com.xiaomi.smarthome"}],"status":"true"}