{"data":[{"count":2271,"imeiCount":1361,"index":"com.tencent.qqmusic","uploadCounts":2271,"uploadImeis":392398},{"count":2249,"imeiCount":1889,"index":"com.sina.weibo","uploadCounts":2249,"uploadImeis":392398},{"count":79,"imeiCount":57,"index":"com.tencent.mm","uploadCounts":79,"uploadImeis":359704},{"count":74,"imeiCount":71,"index":"com.yidian.xiaomi","uploadCounts":74,"uploadImeis":388689},{"count":50,"imeiCount":42,"index":"ctrip.android.view","uploadCounts":50,"uploadImeis":388689},{"count":26,"imeiCount":19,"index":"com.Qunar","uploadCounts":26,"uploadImeis":263028},{"count":21,"imeiCount":20,"index":"com.baidu.BaiduMap","uploadCounts":21,"uploadImeis":243082},{"count":21,"imeiCount":18,"index":"com.cleanmaster.mguard_cn","uploadCounts":21,"uploadImeis":300776},{"count":15,"imeiCount":13,"index":"com.ximalaya.ting.android","uploadCounts":15,"uploadImeis":335042},{"count":13,"imeiCount":12,"index":"com.dianping.v1","uploadCounts":13,"uploadImeis":307539},{"count":2,"imeiCount":2,"index":"com.tuniu.app.ui","uploadCounts":2,"uploadImeis":182880},{"count":1,"imeiCount":1,"index":"cn.wps.moffice_eng","uploadCounts":1,"uploadImeis":27503}],"status":"true"}